airflow/providers/edge3/__init__.py
airflow/providers/edge3/get_provider_info.py
airflow/providers/edge3/version_compat.py
airflow/providers/edge3/cli/__init__.py
airflow/providers/edge3/cli/api_client.py
airflow/providers/edge3/cli/dataclasses.py
airflow/providers/edge3/cli/definition.py
airflow/providers/edge3/cli/edge_command.py
airflow/providers/edge3/cli/signalling.py
airflow/providers/edge3/cli/worker.py
airflow/providers/edge3/example_dags/__init__.py
airflow/providers/edge3/example_dags/integration_test.py
airflow/providers/edge3/example_dags/win_notepad.py
airflow/providers/edge3/example_dags/win_test.py
airflow/providers/edge3/executors/__init__.py
airflow/providers/edge3/executors/edge_executor.py
airflow/providers/edge3/models/__init__.py
airflow/providers/edge3/models/edge_job.py
airflow/providers/edge3/models/edge_logs.py
airflow/providers/edge3/models/edge_worker.py
airflow/providers/edge3/plugins/__init__.py
airflow/providers/edge3/plugins/edge_executor_plugin.py
airflow/providers/edge3/plugins/templates/edge_worker_hosts.html
airflow/providers/edge3/plugins/templates/edge_worker_jobs.html
airflow/providers/edge3/plugins/www/.gitignore
airflow/providers/edge3/plugins/www/.prettierignore
airflow/providers/edge3/plugins/www/.prettierrc
airflow/providers/edge3/plugins/www/README.md
airflow/providers/edge3/plugins/www/eslint.config.js
airflow/providers/edge3/plugins/www/index.html
airflow/providers/edge3/plugins/www/package.json
airflow/providers/edge3/plugins/www/pnpm-lock.yaml
airflow/providers/edge3/plugins/www/testsSetup.ts
airflow/providers/edge3/plugins/www/tsconfig.app.json
airflow/providers/edge3/plugins/www/tsconfig.json
airflow/providers/edge3/plugins/www/tsconfig.lib.json
airflow/providers/edge3/plugins/www/tsconfig.node.json
airflow/providers/edge3/plugins/www/vite.config.ts
airflow/providers/edge3/plugins/www/dist/main.d.ts
airflow/providers/edge3/plugins/www/dist/main.umd.cjs
apache_airflow_providers_edge3-3.0.0.dist-info/entry_points.txt
apache_airflow_providers_edge3-3.0.0.dist-info/licenses/LICENSE
apache_airflow_providers_edge3-3.0.0.dist-info/licenses/NOTICE
apache_airflow_providers_edge3-3.0.0.dist-info/WHEEL
apache_airflow_providers_edge3-3.0.0.dist-info/METADATA
apache_airflow_providers_edge3-3.0.0.dist-info/RECORD
